[
    {
        "key": "dbln",
        "value": "%7B%2261565289884716%22%3A%22gLRa3Mhs%22%7D",
        "domain": "facebook.com",
        "path": "/login/device-based/",
        "hostOnly": false,
        "creation": "2024-11-14T11:41:48.340Z",
        "lastAccessed": "2024-11-14T11:41:48.348Z"
    },
    {
        "key": "datr",
        "value": "UVE1Z_S5rHyBVPA2f96Z-MyO",
        "domain": "facebook.com",
        "path": "/",
        "hostOnly": false,
        "creation": "2024-11-14T11:41:48.348Z",
        "lastAccessed": "2024-11-14T11:41:48.348Z"
    },
    {
        "key": "sb",
        "value": "UVE1Zx2IGStp_-GyeH2S59e8",
        "domain": "facebook.com",
        "path": "/",
        "hostOnly": false,
        "creation": "2024-11-14T11:41:48.348Z",
        "lastAccessed": "2024-11-14T11:41:48.348Z"
    },
    {
        "key": "locale",
        "value": "hi_IN",
        "domain": "facebook.com",
        "path": "/",
        "hostOnly": false,
        "creation": "2024-11-14T11:41:48.348Z",
        "lastAccessed": "2024-11-14T11:41:48.348Z"
    },
    {
        "key": "vpd",
        "value": "v1%3B728x384x2.8125",
        "domain": "facebook.com",
        "path": "/",
        "hostOnly": false,
        "creation": "2024-11-14T11:41:48.348Z",
        "lastAccessed": "2024-11-14T11:41:48.348Z"
    },
    {
        "key": "ps_l",
        "value": "1",
        "domain": "facebook.com",
        "path": "/",
        "hostOnly": false,
        "creation": "2024-11-14T11:41:48.348Z",
        "lastAccessed": "2024-11-14T11:41:48.348Z"
    },
    {
        "key": "ps_n",
        "value": "1",
        "domain": "facebook.com",
        "path": "/",
        "hostOnly": false,
        "creation": "2024-11-14T11:41:48.348Z",
        "lastAccessed": "2024-11-14T11:41:48.348Z"
    },
    {
        "key": "dpr",
        "value": "2.8125",
        "domain": "facebook.com",
        "path": "/",
        "hostOnly": false,
        "creation": "2024-11-14T11:41:48.348Z",
        "lastAccessed": "2024-11-14T11:41:48.348Z"
    },
    {
        "key": "m_pixel_ratio",
        "value": "2.8125",
        "domain": "facebook.com",
        "path": "/",
        "hostOnly": false,
        "creation": "2024-11-14T11:41:48.348Z",
        "lastAccessed": "2024-11-14T11:41:48.349Z"
    },
    {
        "key": "c_user",
        "value": "61565289884716",
        "domain": "facebook.com",
        "path": "/",
        "hostOnly": false,
        "creation": "2024-11-14T11:41:48.349Z",
        "lastAccessed": "2024-11-14T11:41:48.349Z"
    },
    {
        "key": "fr",
        "value": "0a1HVnOUt1CsxgTg5.AWU4T54ZgXL4Z-0nyLweOpZM-lI.BnNVFR..AAA.0.0.BnNdDM.AWWOAHAV-0E",
        "domain": "facebook.com",
        "path": "/",
        "hostOnly": false,
        "creation": "2024-11-14T11:41:48.349Z",
        "lastAccessed": "2024-11-14T11:41:48.349Z"
    },
    {
        "key": "xs",
        "value": "30%3AXrQBWXnZrV4v-g%3A2%3A1731580108%3A-1%3A5047",
        "domain": "facebook.com",
        "path": "/",
        "hostOnly": false,
        "creation": "2024-11-14T11:41:48.349Z",
        "lastAccessed": "2024-11-14T11:41:48.349Z"
    },
    {
        "key": "wd",
        "value": "384x728",
        "domain": "facebook.com",
        "path": "/",
        "hostOnly": false,
        "creation": "2024-11-14T11:41:48.349Z",
        "lastAccessed": "2024-11-14T11:41:48.349Z"
    },
    {
        "key": "wl_cbv",
        "value": "v2%3Bclient_version%3A2673%3Btimestamp%3A1731580115",
        "domain": "facebook.com",
        "path": "/",
        "hostOnly": false,
        "creation": "2024-11-14T11:41:48.349Z",
        "lastAccessed": "2024-11-14T11:41:48.349Z"
    },
    {
        "key": "fbl_st",
        "value": "101329265%3BT%3A28859741",
        "domain": "facebook.com",
        "path": "/",
        "hostOnly": false,
        "creation": "2024-11-14T11:41:48.349Z",
        "lastAccessed": "2024-11-14T11:41:48.349Z"
    }
]
