[
    {
        "key": "dbln",
        "value": "%7B%2261565289884716%22%3A%22gLRa3Mhs%22%2C%2261568803970892%22%3A%22ThN9Z7xi%22%7D",
        "domain": "facebook.com",
        "path": "/login/device-based/",
        "hostOnly": false,
        "creation": "2024-11-14T14:51:41.735Z",
        "lastAccessed": "2024-11-14T14:51:41.736Z"
    },
    {
        "key": "datr",
        "value": "UVE1Z_S5rHyBVPA2f96Z-MyO",
        "domain": "facebook.com",
        "path": "/",
        "hostOnly": false,
        "creation": "2024-11-14T14:51:41.736Z",
        "lastAccessed": "2024-11-14T14:51:41.736Z"
    },
    {
        "key": "sb",
        "value": "UVE1Zx2IGStp_-GyeH2S59e8",
        "domain": "facebook.com",
        "path": "/",
        "hostOnly": false,
        "creation": "2024-11-14T14:51:41.736Z",
        "lastAccessed": "2024-11-14T14:51:41.736Z"
    },
    {
        "key": "vpd",
        "value": "v1%3B728x384x2.8125",
        "domain": "facebook.com",
        "path": "/",
        "hostOnly": false,
        "creation": "2024-11-14T14:51:41.736Z",
        "lastAccessed": "2024-11-14T14:51:41.736Z"
    },
    {
        "key": "ps_l",
        "value": "1",
        "domain": "facebook.com",
        "path": "/",
        "hostOnly": false,
        "creation": "2024-11-14T14:51:41.736Z",
        "lastAccessed": "2024-11-14T14:51:41.736Z"
    },
    {
        "key": "ps_n",
        "value": "1",
        "domain": "facebook.com",
        "path": "/",
        "hostOnly": false,
        "creation": "2024-11-14T14:51:41.736Z",
        "lastAccessed": "2024-11-14T14:51:41.737Z"
    },
    {
        "key": "dpr",
        "value": "2.8125",
        "domain": "facebook.com",
        "path": "/",
        "hostOnly": false,
        "creation": "2024-11-14T14:51:41.737Z",
        "lastAccessed": "2024-11-14T14:51:41.737Z"
    },
    {
        "key": "m_pixel_ratio",
        "value": "2.8125",
        "domain": "facebook.com",
        "path": "/",
        "hostOnly": false,
        "creation": "2024-11-14T14:51:41.737Z",
        "lastAccessed": "2024-11-14T14:51:41.737Z"
    },
    {
        "key": "wd",
        "value": "384x728",
        "domain": "facebook.com",
        "path": "/",
        "hostOnly": false,
        "creation": "2024-11-14T14:51:41.737Z",
        "lastAccessed": "2024-11-14T14:51:41.737Z"
    },
    {
        "key": "c_user",
        "value": "61568803970892",
        "domain": "facebook.com",
        "path": "/",
        "hostOnly": false,
        "creation": "2024-11-14T14:51:41.737Z",
        "lastAccessed": "2024-11-14T14:51:41.737Z"
    },
    {
        "key": "fr",
        "value": "0a1HVnOUt1CsxgTg5.AWXJ2WH-tOnOTPnzNNETMDRw7-Y.BnNVFR..AAA.0.0.BnNg40.AWUGmd7Itr8",
        "domain": "facebook.com",
        "path": "/",
        "hostOnly": false,
        "creation": "2024-11-14T14:51:41.737Z",
        "lastAccessed": "2024-11-14T14:51:41.737Z"
    },
    {
        "key": "xs",
        "value": "35%3Aiu5lN1RRlZ3c9w%3A2%3A1731595830%3A-1%3A-1",
        "domain": "facebook.com",
        "path": "/",
        "hostOnly": false,
        "creation": "2024-11-14T14:51:41.737Z",
        "lastAccessed": "2024-11-14T14:51:41.737Z"
    },
    {
        "key": "locale",
        "value": "en_IN",
        "domain": "facebook.com",
        "path": "/",
        "hostOnly": false,
        "creation": "2024-11-14T14:51:41.737Z",
        "lastAccessed": "2024-11-14T14:51:41.737Z"
    },
    {
        "key": "wl_cbv",
        "value": "v2%3Bclient_version%3A2673%3Btimestamp%3A1731595857",
        "domain": "facebook.com",
        "path": "/",
        "hostOnly": false,
        "creation": "2024-11-14T14:51:41.737Z",
        "lastAccessed": "2024-11-14T14:51:41.737Z"
    },
    {
        "key": "fbl_st",
        "value": "100729268%3BT%3A28859931",
        "domain": "facebook.com",
        "path": "/",
        "hostOnly": false,
        "creation": "2024-11-14T14:51:41.737Z",
        "lastAccessed": "2024-11-14T14:51:41.737Z"
    }
]
